{
  "id": "2024-07-12--alligator-alcatraz-detention-facility-timelin-p3a3b-1",
  "date": "2024-07-12",
  "title": "System Manipulation: Alligator Alcatraz Detention Facility Timeline",
  "summary": "Investigation reveals Alligator Alcatraz Detention Facility Timeline demonstrates coordinated institutional capture through strategic personnel placement, regulatory coordination, and systematic oversight circumvention that compromises democratic governance.",
  "importance": 7,
  "actors": [
    "Corporate Networks",
    "Regulatory Agencies",
    "Political Operatives"
  ],
  "sources": [
    {
      "title": "Analysis: Alligator Alcatraz Detention Facility Timeline",
      "url": "https://trumptyrannytracker.substack.com/strategic-analysis",
      "outlet": "Strategic Analysis"
    }
  ],
  "tags": [
    "institutional-capture",
    "coordination-networks",
    "phase-3-batch2"
  ],
  "status": "confirmed",
  "capture_lanes": [
    "Regulatory Capture"
  ]
}