{
  "date": "2025-09-09",
  "title": "RESEARCH PRIORITY: January 6th Institutional Breakdown and Election Subversion",
  "summary": "Priority Level 10/10. Expected 5 timeline events. Focus areas: election subversion, democratic breakdown, organized violence. Source: Trump Administration Institutional Capture",
  "importance": 10,
  "tags": [
    "research-priority",
    "pdf-ingestion",
    "election subversion"
  ],
  "status": "needs_research",
  "actors": [
    "PDF Ingestion Agent"
  ],
  "notes": "Derived from systematic analysis of Trump Administration Institutional Capture document. Represents high-value research target for kleptocracy timeline development.",
  "id": "2025-09-09--research-priority:-january-6th-institutional-breakdown-and-election-subversion-1757456012",
  "priority_id": "pdf-ingestion-agent"
}