{
  "id": "2025-03-13--inside-elon-musk-s-digital-coup",
  "date": "2025-03-13",
  "title": "Inside Elon Musk’s ‘digital coup’",
  "summary": "Elon Musk's operatives have rewritten federal systems, slashed budgets, and centralized power across government",
  "description": "Elon Musk's operatives have rewritten federal systems, slashed budgets, and centralized power across government",
  "status": "confirmed",
  "importance": 6,
  "location": "Washington, D.C.",
  "actors": [
    "Donald Trump",
    "Trump Administration"
  ],
  "tags": [
    "kleptocracy"
  ],
  "capture_type": "monetizing_position",
  "sources": [
    {
      "title": "Inside Elon Musk’s ‘digital coup’",
      "url": "https://www.wired.com/story/elon-musk-digital-coup-doge-data-ai/",
      "outlet": "Wired",
      "date": "2025-03-13"
    },
    {
      "title": "Timeline Documentation",
      "url": "https://example.com",
      "outlet": "Archive",
      "date": "2025-03-13"
    }
  ],
  "connections": [],
  "patterns": [
    "kleptocratic-capture"
  ],
  "notes": "Event from comprehensive kleptocracy timeline tracking."
}
