{
  "id": "RT-EXP-28753E16",
  "title": "Trilateral Commission 1973 Banking Networks",
  "description": "Map Trilateral Commission founding by David Rockefeller, connecting to international banking coordination and petrodollar system establishment.",
  "priority": "high",
  "tags": [
    "trilateral_commission",
    "rockefeller",
    "international_banking"
  ],
  "decade": "1970s",
  "created": "2025-09-09T21:17:47.657323",
  "status": "pending",
  "category": "expansion_research",
  "connections": [
    "Jules Kroll",
    "CIA networks"
  ]
}